MANIFEST.in
bootstrap.py
buildout.cfg
setup.cfg
setup.py
src/harobed/__init__.py
src/harobed.paster_template.advanced_package.egg-info/PKG-INFO
src/harobed.paster_template.advanced_package.egg-info/SOURCES.txt
src/harobed.paster_template.advanced_package.egg-info/dependency_links.txt
src/harobed.paster_template.advanced_package.egg-info/entry_points.txt
src/harobed.paster_template.advanced_package.egg-info/namespace_packages.txt
src/harobed.paster_template.advanced_package.egg-info/not-zip-safe
src/harobed.paster_template.advanced_package.egg-info/requires.txt
src/harobed.paster_template.advanced_package.egg-info/top_level.txt
src/harobed/paster_template/__init__.py
src/harobed/paster_template/advanced_package/__init__.py
src/harobed/paster_template/advanced_package/templates/.__init__.py
src/harobed/paster_template/advanced_package/templates/.namespace__init__.py
src/harobed/paster_template/advanced_package/templates/bootstrap.py
src/harobed/paster_template/advanced_package/templates/buildout.cfg
src/harobed/paster_template/advanced_package/templates/setup.cfg
src/harobed/paster_template/advanced_package/templates/setup.py_tmpl
tests/__init__.py
tests/test.py
tests/my.name.space/setup.cfg
tests/my.name.space/setup.py
tests/my.name.space/src/my/__init__.py
tests/my.name.space/src/my.name.space.egg-info/PKG-INFO
tests/my.name.space/src/my.name.space.egg-info/SOURCES.txt
tests/my.name.space/src/my.name.space.egg-info/dependency_links.txt
tests/my.name.space/src/my.name.space.egg-info/entry_points.txt
tests/my.name.space/src/my.name.space.egg-info/namespace_packages.txt
tests/my.name.space/src/my.name.space.egg-info/not-zip-safe
tests/my.name.space/src/my.name.space.egg-info/top_level.txt
tests/my.name.space/src/my/name/__init__.py
tests/my.name.space/src/my/name/space/__init__.py
tests/simple_with_buildout/bootstrap.py
tests/simple_with_buildout/buildout.cfg
tests/simple_with_buildout/setup.cfg
tests/simple_with_buildout/setup.py
tests/simple_with_buildout/src/simple_with_buildout/__init__.py
tests/simple_with_buildout/src/simple_with_buildout.egg-info/PKG-INFO
tests/simple_with_buildout/src/simple_with_buildout.egg-info/SOURCES.txt
tests/simple_with_buildout/src/simple_with_buildout.egg-info/dependency_links.txt
tests/simple_with_buildout/src/simple_with_buildout.egg-info/entry_points.txt
tests/simple_with_buildout/src/simple_with_buildout.egg-info/not-zip-safe
tests/simple_with_buildout/src/simple_with_buildout.egg-info/top_level.txt