Metadata-Version: 1.0
Name: harobed.paster-template.advanced-package
Version: 0.1
Summary: PasteScript template to create advanced setuptools-enabled package with buildout and namespace support
Home-page: http://code.google.com/p/paste-script-advanced-package-template/
Author: KLEIN Stephane
Author-email: stephane@harobed.org
License: GNU General Public License v3
Platform: UNKNOWN
